synthpose/__init__.py
synthpose/adapters/__init__.py
synthpose/adapters/detectors.py
synthpose/adapters/estimators.py
synthpose/adapters/serializers.py
synthpose/adapters/video.py
synthpose/adapters/visualization.py
synthpose/application/__init__.py
synthpose/application/processor.py
synthpose/domain/__init__.py
synthpose/domain/entities.py
synthpose/domain/interfaces.py
synthpose/infrastructure/__init__.py
synthpose/infrastructure/cli.py
synthpose/infrastructure/config.py
synthpose-0.1.0.dist-info/entry_points.txt
synthpose-0.1.0.dist-info/METADATA
synthpose-0.1.0.dist-info/WHEEL
synthpose-0.1.0.dist-info/RECORD
