Metadata-Version: 2.4
Name: synthpose
Version: 0.1.0
Summary: A clean architecture implementation of SynthPose for pose estimation.
Author: SynthPose Team
Requires-Python: >=3.10,<4.0
Classifier: Programming Language :: Python :: 3
Classifier: Programming Language :: Python :: 3.10
Classifier: Programming Language :: Python :: 3.11
Classifier: Programming Language :: Python :: 3.12
Classifier: Programming Language :: Python :: 3.13
Classifier: Programming Language :: Python :: 3.14
Requires-Dist: numpy (>=1.24.0)
Requires-Dist: opencv-python (>=4.8.0)
Requires-Dist: pillow (>=10.0.0)
Requires-Dist: pydantic (>=2.0,<3.0)
Requires-Dist: pydantic-settings (>=2.0,<3.0)
Requires-Dist: pyyaml (>=6.0,<7.0)
Requires-Dist: rtmlib (>=0.0.13)
Requires-Dist: torch (>=2.0.0)
Requires-Dist: transformers (>=4.36.0)
Requires-Dist: typer (>=0.9.0,<0.10.0)
